KemoAuth.py
KemoAuth-2.0.dist-info/METADATA
KemoAuth-2.0.dist-info/WHEEL
KemoAuth-2.0.dist-info/top_level.txt
KemoAuth-2.0.dist-info/RECORD
