Metadata-Version: 2.2
Name: KemoAuth
Version: 2.0
Summary: Kemoauth is a Simple Key System
Home-page: 
Author: DewzaCSharp
Author-email: dewzacsharp@gmail.com
Classifier: Programming Language :: Python :: 3
Classifier: License :: OSI Approved :: MIT License
Classifier: Operating System :: OS Independent
Requires-Dist: setuptools
Requires-Dist: wheel
Requires-Dist: asyncio
Requires-Dist: typing
Requires-Dist: psutil
Requires-Dist: uuid
Dynamic: author
Dynamic: author-email
Dynamic: classifier
Dynamic: description
Dynamic: description-content-type
Dynamic: requires-dist
Dynamic: summary
